{
	"archive" : {},
	"artifacts" : 
	[
		{
			"path" : "zephyr/kernel/libkernel.a"
		}
	],
	"backtrace" : 1,
	"backtraceGraph" : 
	{
		"commands" : 
		[
			"add_library",
			"add_dependencies",
			"add_compile_options",
			"target_link_libraries",
			"set_target_properties",
			"target_include_directories",
			"target_sources",
			"target_sources_ifdef"
		],
		"files" : 
		[
			"/opt/nordic/ncs/v2.6.0/zephyr/kernel/CMakeLists.txt",
			"/opt/nordic/ncs/v2.6.0/zephyr/CMakeLists.txt",
			"/opt/nordic/ncs/v2.6.0/zephyr/cmake/modules/extensions.cmake"
		],
		"nodes" : 
		[
			{
				"file" : 0
			},
			{
				"command" : 0,
				"file" : 0,
				"line" : 96,
				"parent" : 0
			},
			{
				"file" : 1
			},
			{
				"command" : 1,
				"file" : 1,
				"line" : 816,
				"parent" : 2
			},
			{
				"command" : 1,
				"file" : 0,
				"line" : 151,
				"parent" : 0
			},
			{
				"command" : 2,
				"file" : 0,
				"line" : 48,
				"parent" : 0
			},
			{
				"command" : 3,
				"file" : 0,
				"line" : 147,
				"parent" : 0
			},
			{
				"command" : 4,
				"file" : 0,
				"line" : 101,
				"parent" : 0
			},
			{
				"command" : 5,
				"file" : 0,
				"line" : 142,
				"parent" : 0
			},
			{
				"command" : 7,
				"file" : 0,
				"line" : 109,
				"parent" : 0
			},
			{
				"command" : 6,
				"file" : 2,
				"line" : 1702,
				"parent" : 9
			},
			{
				"command" : 7,
				"file" : 0,
				"line" : 112,
				"parent" : 0
			},
			{
				"command" : 6,
				"file" : 2,
				"line" : 1702,
				"parent" : 11
			},
			{
				"command" : 6,
				"file" : 0,
				"line" : 119,
				"parent" : 0
			},
			{
				"command" : 6,
				"file" : 0,
				"line" : 139,
				"parent" : 0
			}
		]
	},
	"compileGroups" : 
	[
		{
			"compileCommandFragments" : 
			[
				{
					"fragment" : "-g"
				},
				{
					"backtrace" : 5,
					"fragment" : "-Wshadow"
				},
				{
					"backtrace" : 6,
					"fragment" : "-fno-strict-aliasing"
				},
				{
					"backtrace" : 6,
					"fragment" : "-Os"
				},
				{
					"backtrace" : 6,
					"fragment" : "-imacros"
				},
				{
					"backtrace" : 6,
					"fragment" : "/Users/tomaitagaki/Documents/GitHub/millimobile-firmware/build/zephyr/include/generated/autoconf.h"
				},
				{
					"backtrace" : 6,
					"fragment" : "-fno-printf-return-value"
				},
				{
					"backtrace" : 6,
					"fragment" : "-fno-common"
				},
				{
					"backtrace" : 6,
					"fragment" : "-g"
				},
				{
					"backtrace" : 6,
					"fragment" : "-gdwarf-4"
				},
				{
					"backtrace" : 6,
					"fragment" : "-fdiagnostics-color=always"
				},
				{
					"backtrace" : 6,
					"fragment" : "-mcpu=cortex-m33"
				},
				{
					"backtrace" : 6,
					"fragment" : "-mthumb"
				},
				{
					"backtrace" : 6,
					"fragment" : "-mabi=aapcs"
				},
				{
					"backtrace" : 6,
					"fragment" : "-mfp16-format=ieee"
				},
				{
					"backtrace" : 6,
					"fragment" : "-mtp=soft"
				},
				{
					"backtrace" : 6,
					"fragment" : "--sysroot=/opt/nordic/ncs/toolchains/580e4ef81c/opt/zephyr-sdk/arm-zephyr-eabi/arm-zephyr-eabi"
				},
				{
					"backtrace" : 6,
					"fragment" : "-imacros"
				},
				{
					"backtrace" : 6,
					"fragment" : "/opt/nordic/ncs/v2.6.0/zephyr/include/zephyr/toolchain/zephyr_stdint.h"
				},
				{
					"backtrace" : 6,
					"fragment" : "-Wall"
				},
				{
					"backtrace" : 6,
					"fragment" : "-Wformat"
				},
				{
					"backtrace" : 6,
					"fragment" : "-Wformat-security"
				},
				{
					"backtrace" : 6,
					"fragment" : "-Wno-format-zero-length"
				},
				{
					"backtrace" : 6,
					"fragment" : "-Wno-pointer-sign"
				},
				{
					"backtrace" : 6,
					"fragment" : "-Wpointer-arith"
				},
				{
					"backtrace" : 6,
					"fragment" : "-Wexpansion-to-defined"
				},
				{
					"backtrace" : 6,
					"fragment" : "-Wno-unused-but-set-variable"
				},
				{
					"backtrace" : 6,
					"fragment" : "-Werror=implicit-int"
				},
				{
					"backtrace" : 6,
					"fragment" : "-fno-pic"
				},
				{
					"backtrace" : 6,
					"fragment" : "-fno-pie"
				},
				{
					"backtrace" : 6,
					"fragment" : "-fno-asynchronous-unwind-tables"
				},
				{
					"backtrace" : 6,
					"fragment" : "-ftls-model=local-exec"
				},
				{
					"backtrace" : 6,
					"fragment" : "-fno-reorder-functions"
				},
				{
					"backtrace" : 6,
					"fragment" : "--param=min-pagesize=0"
				},
				{
					"backtrace" : 6,
					"fragment" : "-fno-defer-pop"
				},
				{
					"backtrace" : 6,
					"fragment" : "-fmacro-prefix-map=/Users/tomaitagaki/Documents/GitHub/millimobile-firmware=CMAKE_SOURCE_DIR"
				},
				{
					"backtrace" : 6,
					"fragment" : "-fmacro-prefix-map=/opt/nordic/ncs/v2.6.0/zephyr=ZEPHYR_BASE"
				},
				{
					"backtrace" : 6,
					"fragment" : "-fmacro-prefix-map=/opt/nordic/ncs/v2.6.0=WEST_TOPDIR"
				},
				{
					"backtrace" : 6,
					"fragment" : "-ffunction-sections"
				},
				{
					"backtrace" : 6,
					"fragment" : "-fdata-sections"
				},
				{
					"backtrace" : 6,
					"fragment" : "--specs=picolibc.specs"
				},
				{
					"backtrace" : 6,
					"fragment" : "-std=c99"
				}
			],
			"defines" : 
			[
				{
					"backtrace" : 6,
					"define" : "KERNEL"
				},
				{
					"backtrace" : 6,
					"define" : "NRF5340_XXAA_APPLICATION"
				},
				{
					"backtrace" : 6,
					"define" : "NRF_SKIP_FICR_NS_COPY_TO_RAM"
				},
				{
					"backtrace" : 6,
					"define" : "PICOLIBC_LONG_LONG_PRINTF_SCANF"
				},
				{
					"backtrace" : 6,
					"define" : "USE_PARTITION_MANAGER=1"
				},
				{
					"backtrace" : 6,
					"define" : "_FORTIFY_SOURCE=1"
				},
				{
					"backtrace" : 6,
					"define" : "_POSIX_C_SOURCE=200809"
				},
				{
					"backtrace" : 6,
					"define" : "__LINUX_ERRNO_EXTENSIONS__"
				},
				{
					"backtrace" : 6,
					"define" : "__PROGRAM_START"
				},
				{
					"backtrace" : 7,
					"define" : "__ZEPHYR_SUPERVISOR__"
				},
				{
					"backtrace" : 6,
					"define" : "__ZEPHYR__=1"
				}
			],
			"includes" : 
			[
				{
					"backtrace" : 8,
					"path" : "/opt/nordic/ncs/v2.6.0/zephyr/kernel/include"
				},
				{
					"backtrace" : 8,
					"path" : "/opt/nordic/ncs/v2.6.0/zephyr/arch/arm/include"
				},
				{
					"backtrace" : 6,
					"path" : "/opt/nordic/ncs/v2.6.0/zephyr/include"
				},
				{
					"backtrace" : 6,
					"path" : "/Users/tomaitagaki/Documents/GitHub/millimobile-firmware/build/zephyr/include/generated"
				},
				{
					"backtrace" : 6,
					"path" : "/opt/nordic/ncs/v2.6.0/zephyr/soc/arm/nordic_nrf/nrf53"
				},
				{
					"backtrace" : 6,
					"path" : "/opt/nordic/ncs/v2.6.0/zephyr/soc/common/nordic_nrf/."
				},
				{
					"backtrace" : 6,
					"path" : "/opt/nordic/ncs/v2.6.0/zephyr/soc/arm/nordic_nrf/common/."
				},
				{
					"backtrace" : 6,
					"path" : "/opt/nordic/ncs/v2.6.0/zephyr/subsys/bluetooth"
				},
				{
					"backtrace" : 6,
					"path" : "/opt/nordic/ncs/v2.6.0/nrf/include"
				},
				{
					"backtrace" : 6,
					"path" : "/opt/nordic/ncs/v2.6.0/nrf/tests/include"
				},
				{
					"backtrace" : 6,
					"path" : "/opt/nordic/ncs/v2.6.0/modules/hal/cmsis/CMSIS/Core/Include"
				},
				{
					"backtrace" : 6,
					"path" : "/opt/nordic/ncs/v2.6.0/zephyr/modules/cmsis/."
				},
				{
					"backtrace" : 6,
					"path" : "/opt/nordic/ncs/v2.6.0/modules/hal/nordic/nrfx"
				},
				{
					"backtrace" : 6,
					"path" : "/opt/nordic/ncs/v2.6.0/modules/hal/nordic/nrfx/drivers/include"
				},
				{
					"backtrace" : 6,
					"path" : "/opt/nordic/ncs/v2.6.0/modules/hal/nordic/nrfx/mdk"
				},
				{
					"backtrace" : 6,
					"path" : "/opt/nordic/ncs/v2.6.0/zephyr/modules/hal_nordic/nrfx/."
				},
				{
					"backtrace" : 6,
					"path" : "/Users/tomaitagaki/Documents/GitHub/millimobile-firmware/build/modules/libmetal/libmetal/lib/include"
				},
				{
					"backtrace" : 6,
					"path" : "/opt/nordic/ncs/v2.6.0/modules/lib/open-amp/open-amp/lib/include"
				},
				{
					"backtrace" : 6,
					"path" : "/opt/nordic/ncs/v2.6.0/modules/crypto/tinycrypt/lib/include"
				},
				{
					"backtrace" : 6,
					"path" : "/opt/nordic/ncs/v2.6.0/nrfxlib/softdevice_controller/include"
				},
				{
					"backtrace" : 6,
					"isSystem" : true,
					"path" : "/opt/nordic/ncs/v2.6.0/zephyr/lib/libc/common/include"
				},
				{
					"backtrace" : 6,
					"isSystem" : true,
					"path" : "/opt/nordic/ncs/v2.6.0/nrfxlib/crypto/nrf_cc312_platform/include"
				}
			],
			"language" : "C",
			"sourceIndexes" : 
			[
				0,
				1,
				2,
				3,
				4,
				5,
				6,
				7,
				8,
				9,
				10,
				11,
				12,
				13,
				14,
				15,
				16,
				17,
				18,
				19,
				20,
				21,
				22,
				23,
				24,
				25,
				26,
				27
			]
		}
	],
	"dependencies" : 
	[
		{
			"backtrace" : 3,
			"id" : "syscall_list_h_target::@d36e55b69c1b90fb26b2"
		},
		{
			"backtrace" : 3,
			"id" : "driver_validation_h_target::@d36e55b69c1b90fb26b2"
		},
		{
			"backtrace" : 3,
			"id" : "kobj_types_h_target::@d36e55b69c1b90fb26b2"
		},
		{
			"backtrace" : 4,
			"id" : "zephyr_generated_headers::@d36e55b69c1b90fb26b2"
		}
	],
	"id" : "kernel::@84e783bf488a9f887759",
	"name" : "kernel",
	"nameOnDisk" : "libkernel.a",
	"paths" : 
	{
		"build" : "zephyr/kernel",
		"source" : "/opt/nordic/ncs/v2.6.0/zephyr/kernel"
	},
	"sourceGroups" : 
	[
		{
			"name" : "Source Files",
			"sourceIndexes" : 
			[
				0,
				1,
				2,
				3,
				4,
				5,
				6,
				7,
				8,
				9,
				10,
				11,
				12,
				13,
				14,
				15,
				16,
				17,
				18,
				19,
				20,
				21,
				22,
				23,
				24,
				25,
				26,
				27
			]
		}
	],
	"sources" : 
	[
		{
			"backtrace" : 1,
			"compileGroupIndex" : 0,
			"path" : "/opt/nordic/ncs/v2.6.0/zephyr/kernel/main_weak.c",
			"sourceGroupIndex" : 0
		},
		{
			"backtrace" : 1,
			"compileGroupIndex" : 0,
			"path" : "/opt/nordic/ncs/v2.6.0/zephyr/kernel/banner.c",
			"sourceGroupIndex" : 0
		},
		{
			"backtrace" : 1,
			"compileGroupIndex" : 0,
			"path" : "/opt/nordic/ncs/v2.6.0/zephyr/kernel/busy_wait.c",
			"sourceGroupIndex" : 0
		},
		{
			"backtrace" : 1,
			"compileGroupIndex" : 0,
			"path" : "/opt/nordic/ncs/v2.6.0/zephyr/kernel/device.c",
			"sourceGroupIndex" : 0
		},
		{
			"backtrace" : 1,
			"compileGroupIndex" : 0,
			"path" : "/opt/nordic/ncs/v2.6.0/zephyr/kernel/errno.c",
			"sourceGroupIndex" : 0
		},
		{
			"backtrace" : 1,
			"compileGroupIndex" : 0,
			"path" : "/opt/nordic/ncs/v2.6.0/zephyr/kernel/fatal.c",
			"sourceGroupIndex" : 0
		},
		{
			"backtrace" : 1,
			"compileGroupIndex" : 0,
			"path" : "/opt/nordic/ncs/v2.6.0/zephyr/kernel/init.c",
			"sourceGroupIndex" : 0
		},
		{
			"backtrace" : 1,
			"compileGroupIndex" : 0,
			"path" : "/opt/nordic/ncs/v2.6.0/zephyr/kernel/kheap.c",
			"sourceGroupIndex" : 0
		},
		{
			"backtrace" : 1,
			"compileGroupIndex" : 0,
			"path" : "/opt/nordic/ncs/v2.6.0/zephyr/kernel/mem_slab.c",
			"sourceGroupIndex" : 0
		},
		{
			"backtrace" : 1,
			"compileGroupIndex" : 0,
			"path" : "/opt/nordic/ncs/v2.6.0/zephyr/kernel/thread.c",
			"sourceGroupIndex" : 0
		},
		{
			"backtrace" : 1,
			"compileGroupIndex" : 0,
			"path" : "/opt/nordic/ncs/v2.6.0/zephyr/kernel/version.c",
			"sourceGroupIndex" : 0
		},
		{
			"backtrace" : 1,
			"compileGroupIndex" : 0,
			"path" : "/opt/nordic/ncs/v2.6.0/zephyr/kernel/idle.c",
			"sourceGroupIndex" : 0
		},
		{
			"backtrace" : 1,
			"compileGroupIndex" : 0,
			"path" : "/opt/nordic/ncs/v2.6.0/zephyr/kernel/mailbox.c",
			"sourceGroupIndex" : 0
		},
		{
			"backtrace" : 1,
			"compileGroupIndex" : 0,
			"path" : "/opt/nordic/ncs/v2.6.0/zephyr/kernel/msg_q.c",
			"sourceGroupIndex" : 0
		},
		{
			"backtrace" : 1,
			"compileGroupIndex" : 0,
			"path" : "/opt/nordic/ncs/v2.6.0/zephyr/kernel/mutex.c",
			"sourceGroupIndex" : 0
		},
		{
			"backtrace" : 1,
			"compileGroupIndex" : 0,
			"path" : "/opt/nordic/ncs/v2.6.0/zephyr/kernel/queue.c",
			"sourceGroupIndex" : 0
		},
		{
			"backtrace" : 1,
			"compileGroupIndex" : 0,
			"path" : "/opt/nordic/ncs/v2.6.0/zephyr/kernel/sem.c",
			"sourceGroupIndex" : 0
		},
		{
			"backtrace" : 1,
			"compileGroupIndex" : 0,
			"path" : "/opt/nordic/ncs/v2.6.0/zephyr/kernel/stack.c",
			"sourceGroupIndex" : 0
		},
		{
			"backtrace" : 1,
			"compileGroupIndex" : 0,
			"path" : "/opt/nordic/ncs/v2.6.0/zephyr/kernel/system_work_q.c",
			"sourceGroupIndex" : 0
		},
		{
			"backtrace" : 1,
			"compileGroupIndex" : 0,
			"path" : "/opt/nordic/ncs/v2.6.0/zephyr/kernel/work.c",
			"sourceGroupIndex" : 0
		},
		{
			"backtrace" : 1,
			"compileGroupIndex" : 0,
			"path" : "/opt/nordic/ncs/v2.6.0/zephyr/kernel/sched.c",
			"sourceGroupIndex" : 0
		},
		{
			"backtrace" : 1,
			"compileGroupIndex" : 0,
			"path" : "/opt/nordic/ncs/v2.6.0/zephyr/kernel/condvar.c",
			"sourceGroupIndex" : 0
		},
		{
			"backtrace" : 1,
			"compileGroupIndex" : 0,
			"path" : "/opt/nordic/ncs/v2.6.0/zephyr/kernel/xip.c",
			"sourceGroupIndex" : 0
		},
		{
			"backtrace" : 10,
			"compileGroupIndex" : 0,
			"path" : "/opt/nordic/ncs/v2.6.0/zephyr/kernel/timeout.c",
			"sourceGroupIndex" : 0
		},
		{
			"backtrace" : 10,
			"compileGroupIndex" : 0,
			"path" : "/opt/nordic/ncs/v2.6.0/zephyr/kernel/timer.c",
			"sourceGroupIndex" : 0
		},
		{
			"backtrace" : 12,
			"compileGroupIndex" : 0,
			"path" : "/opt/nordic/ncs/v2.6.0/zephyr/kernel/poll.c",
			"sourceGroupIndex" : 0
		},
		{
			"backtrace" : 13,
			"compileGroupIndex" : 0,
			"path" : "/opt/nordic/ncs/v2.6.0/zephyr/kernel/mempool.c",
			"sourceGroupIndex" : 0
		},
		{
			"backtrace" : 14,
			"compileGroupIndex" : 0,
			"path" : "/opt/nordic/ncs/v2.6.0/zephyr/kernel/dynamic_disabled.c",
			"sourceGroupIndex" : 0
		}
	],
	"type" : "STATIC_LIBRARY"
}
